failtrace_app/__init__.py
failtrace_app/__main__.py
failtrace_app/analysis/__init__.py
failtrace_app/analysis/critical_path.py
failtrace_app/analysis/critical_path_extractor.py
failtrace_app/analysis/function_extractor.py
failtrace_app/analysis/locator.py
failtrace_app/analysis/mapper.py
failtrace_app/analysis/summarizer.py
failtrace_app/cli/__init__.py
failtrace_app/cli/main.py
failtrace_app/graph/__init__.py
failtrace_app/graph/graph_builder/__init__.py
failtrace_app/graph/graph_builder/base.py
failtrace_app/graph/graph_builder/csharp_graph.py
failtrace_app/graph/graph_builder/csharp_graph_builder.py
failtrace_app/graph/graph_builder/detector.py
failtrace_app/graph/graph_builder/java_graph.py
failtrace_app/graph/graph_builder/java_graph_builder.py
failtrace_app/graph/graph_builder/plugins.py
failtrace_app/graph/graph_builder/python_graph.py
failtrace_app/graph/graph_builder/python_graph_builder.py
failtrace_app/graph/graph_utils/__init__.py
failtrace_app/graph/graph_utils/locator_ranker.py
failtrace_app/graph/graph_utils/node_summarizer.py
failtrace_app/graph/graph_utils/path_enricher.py
failtrace_app/lib/bindings/utils.js
failtrace_app/lib/tom-select/tom-select.complete.min.js
failtrace_app/lib/tom-select/tom-select.css
failtrace_app/lib/vis-9.1.2/vis-network.css
failtrace_app/lib/vis-9.1.2/vis-network.min.js
failtrace_app/llm/__init__.py
failtrace_app/llm/avalai_client.py
failtrace_app/llm/few_shots/csharp_async_race.json
failtrace_app/llm/few_shots/java_nullpointer.json
failtrace_app/llm/few_shots/python_unit_fail.json
failtrace_app/llm/few_shots_loader.py
failtrace_app/llm/function_extractor.py
failtrace_app/llm/prompt_generator.py
failtrace_app/llm/structured_prompt_builder.py
failtrace_app/tests/__init__.py
failtrace_app/tests/test_main.py
failtrace_app/utils/__init__.py
failtrace_app/utils/file_ops.py
failtrace_app/utils/logs_parser.py
failtrace_app/utils/normalize.py
failtrace_app/utils/report_renderer.py
failtrace_app/utils/visualizer.py
failtrace_app-0.1.0.dist-info/entry_points.txt
failtrace_app-0.1.0.dist-info/METADATA
failtrace_app-0.1.0.dist-info/WHEEL
failtrace_app-0.1.0.dist-info/RECORD
