Metadata-Version: 2.3
Name: failtrace-app
Version: 0.1.0
Summary: Leveraging Large Language Models for Automated Test Results Analysis
License: MIT
Keywords: cli,testing,llm,analysis
Author: Mohadese Akhoondy
Author-email: m.akhoondy1381@gmail.com
Requires-Python: >=3.12
Classifier: Environment :: Console
Classifier: License :: OSI Approved :: MIT License
Classifier: Programming Language :: Python :: 3.12
Classifier: Operating System :: OS Independent
Requires-Dist: javalang (>=0.13.0,<0.14.0)
Requires-Dist: libcst (>=1.8.2,<2.0.0)
Requires-Dist: mypy (>=1.17.1,<2.0.0)
Requires-Dist: networkx (>=3.5,<4.0)
Requires-Dist: openai (>=1.99.9,<2.0.0)
Requires-Dist: pycg (>=0.0.8,<0.0.9)
Requires-Dist: pylint (>=3.3.8,<4.0.0)
Requires-Dist: pytest (>=8.4.1,<9.0.0)
Requires-Dist: pytest-json-report (>=1.5.0,<2.0.0)
Requires-Dist: pyvis (>=0.3.2,<0.4.0)
Requires-Dist: requests (>=2.32.4,<3.0.0)
Requires-Dist: rich (>=14.1.0,<15.0.0)
Requires-Dist: tree-sitter (>=0.25.1,<0.26.0)
Requires-Dist: tree-sitter-c-sharp (==0.23.1)
